rlogfi/README.MD
rlogfi/__init__.py
rlogfi/requirements.txt
rlogfi/thirdparty.json
rlogfi-0.10.dist-info/LICENSE.rst
rlogfi-0.10.dist-info/METADATA
rlogfi-0.10.dist-info/WHEEL
rlogfi-0.10.dist-info/top_level.txt
rlogfi-0.10.dist-info/RECORD
