Metadata-Version: 2.1
Name: rlogfi
Version: 0.10
Summary: Detached PowerShell interactive session, but with full control
Home-page: https://github.com/hansalemaos/rlogfi
Author: Johannes Fischer
Author-email: aulasparticularesdealemaosp@gmail.com
License: MIT
Keywords: PowerShell,Asyncio
Classifier: Development Status :: 4 - Beta
Classifier: Programming Language :: Python :: 3 :: Only
Classifier: Programming Language :: Python :: 3.10
Classifier: Topic :: Software Development :: Libraries :: Python Modules
Classifier: Topic :: Utilities
License-File: LICENSE.rst
Requires-Dist: aiofiles
Requires-Dist: tkkillablethreads
Requires-Dist: touchtouch
